README.md
setup.cfg
setup.py
hyperio/__init__.py
hyperio/main.py
hyperio/reporting.py
hyperio.egg-info/PKG-INFO
hyperio.egg-info/SOURCES.txt
hyperio.egg-info/dependency_links.txt
hyperio.egg-info/requires.txt
hyperio.egg-info/top_level.txt
hyperio/data/__init__.py
hyperio/data/data.py
hyperio/utils/__init__.py
hyperio/utils/template.py
hyperio/utils/utils.py