Metadata-Version: 1.1
Name: hyperio
Version: 0.1.6
Summary: Hyperio Hyperparameter Scanner for Keras
Home-page: http://autonom.io
Author: Mikko Kotila
Author-email: mailme@mikkokotila.com
License: MIT
Download-URL: https://github.com/autonomio/hyperio/
Platform: UNKNOWN
Classifier: Intended Audience :: Science/Research
Classifier: Programming Language :: Python :: 2.7
Classifier: License :: OSI Approved :: MIT License
Classifier: Topic :: Scientific/Engineering :: Human Machine Interfaces
Classifier: Topic :: Scientific/Engineering :: Artificial Intelligence
Classifier: Topic :: Scientific/Engineering :: Mathematics
Classifier: Operating System :: POSIX
Classifier: Operating System :: Unix
Classifier: Operating System :: MacOS
